{
  "wlbWellboreName": "34/12-1",
  "wlbWell": "34/12-1",
  "wlbDrillingOperator": "Eni Norge AS",
  "wlbProductionLicence": "293 ",
  "wlbPurpose": "WILDCAT",
  "wlbStatus": "P&A",
  "wlbContent": "GAS/CONDENSATE",
  "wlbWellType": "EXPLORATION",
  "wlbSubSea": " NO",
  "wlbEntryDate": "03.11.2007",
  "wlbCompletionDate": "30.04.2008",
  "wlbField": "",
  "wlbDrillPermit": "1162-L",
  "wlbDiscovery": "34/12-1 (Afrodite)",
  "wlbDiscoveryWellbore": "YES",
  "wlbBottomHoleTemperature": "168",
  "wlbSeismicLocation": "PSDM en 04m01-line 2770 & trace 6120",
  "wlbMaxInclation": "5.60",
  "wlbKellyBushElevation": "23.0",
  "wlbFinalVerticalDepth": "4711.0",
  "wlbTotalDepth": "4713.0",
  "wlbWaterDepth": "373.0",
  "wlbKickOffPoint": "",
  "wlbAgeAtTd": "EARLY JURASSIC      ",
  "wlbFormationAtTd": "COOK FM             ",
  "wlbMainArea": "North sea",
  "wlbDrillingFacility": "TRANSOCEAN LEADER",
  "wlbFacilityTypeDrilling": "SEMISUB STEEL",
  "wlbDrillingFacilityFixedOrMoveable": "MOVEABLE",
  "wlbLicensingActivity": "NST2002",
  "wlbMultilateral": "NO",
  "wlbPurposePlanned": "WILDCAT",
  "wlbEntryYear": "2007",
  "wlbCompletionYear": "2008",
  "wlbReclassFromWellbore": "",
  "wlbReentryExplorationActivity": "",
  "wlbPlotSymbol": "17",
  "wlbFormationWithHc1": "BRENT GP",
  "wlbAgeWithHc1": "MIDDLE JURASSIC",
  "wlbFormationWithHc2": "",
  "wlbAgeWithHc2": "",
  "wlbFormationWithHc3": "                    ",
  "wlbAgeWithHc3": "                    ",
  "wlbDrillingDays": "180",
  "wlbReentry": "NO",
  "wlbGeodeticDatum": "ED50  ",
  "wlbNsDeg": "61",
  "wlbNsMin": "13",
  "wlbNsSec": "19.88",
  "wlbNsCode": "N",
  "wlbEwDeg": "2",
  "wlbEwMin": "59",
  "wlbEwSec": "55.62",
  "wlbEwCode": "E",
  "wlbNsDecDeg": "61.222189",
  "wlbEwDesDeg": "2.998783",
  "wlbNsUtm": "6787697.57",
  "wlbEwUtm": "499934.65",
  "wlbUtmZone": "31",
  "wlbNamePart1": "34",
  "wlbNamePart2": "12",
  "wlbNamePart3": " ",
  "wlbNamePart4": "1",
  "wlbNamePart5": "",
  "wlbNamePart6": "",
  "wlbPressReleaseUrl": "http://www.npd.no/no/Nyheter/Resultat-av-leteboring/2008/34-12-1/",
  "wlbFactPageUrl": "http://factpages.npd.no/FactPages/Default.aspx?nav1=wellbore&nav2=PageView|Exploration|All&nav3=5684",
  "wlbFactMapUrl": "http://gis.npd.no/factmaps/html_21/?run=WellboreExpByNPDID&scale=100000&NPDID=5684",
  "wlbDiskosWellboreType": "initial             ",
  "wlbDiskosWellboreParent": "                                        ",
  "wlbWdssQcDate": "30.04.2010",
  "wlbReleasedDate": "30.04.2010",
  "wlbNpdidWellbore": "5684",
  "dscNpdidDiscovery": "4972705",
  "fldNpdidField": "",
  "fclNpdidFacilityDrilling": "296677",
  "wlbNpdidWellboreReclass": "0",
  "prlNpdidProductionLicence": "2407711"
}