{
  "wlbWellboreName": "9/2-9 S",
  "wlbWell": "9/2-9",
  "wlbDrillingOperator": "Den norske stats oljeselskap a.s",
  "wlbProductionLicence": "114 ",
  "wlbPurpose": "WILDCAT",
  "wlbStatus": "RE-CLASS TO DEV",
  "wlbContent": "OIL",
  "wlbWellType": "EXPLORATION",
  "wlbSubSea": " NO",
  "wlbEntryDate": "29.06.1999",
  "wlbCompletionDate": "18.10.1999",
  "wlbField": "YME",
  "wlbDrillPermit": "948-L",
  "wlbDiscovery": "9/2-9 S",
  "wlbDiscoveryWellbore": "YES",
  "wlbBottomHoleTemperature": "0",
  "wlbSeismicLocation": "ST 9413- INLINE 646 & X-LINE 646",
  "wlbMaxInclation": "0.00",
  "wlbKellyBushElevation": "25.0",
  "wlbFinalVerticalDepth": "3386.0",
  "wlbTotalDepth": "4367.0",
  "wlbWaterDepth": "77.0",
  "wlbKickOffPoint": "",
  "wlbAgeAtTd": "MIDDLE JURASSIC     ",
  "wlbFormationAtTd": "BRYNE FM            ",
  "wlbMainArea": "North sea",
  "wlbDrillingFacility": "BYFORD DOLPHIN",
  "wlbFacilityTypeDrilling": "SEMISUB STEEL",
  "wlbDrillingFacilityFixedOrMoveable": "MOVEABLE",
  "wlbLicensingActivity": "10-A",
  "wlbMultilateral": "NO",
  "wlbPurposePlanned": "WILDCAT",
  "wlbEntryYear": "1999",
  "wlbCompletionYear": "1999",
  "wlbReclassFromWellbore": "9/2-B-4 H  ",
  "wlbReentryExplorationActivity": "",
  "wlbPlotSymbol": "5",
  "wlbFormationWithHc1": "SANDNES FM",
  "wlbAgeWithHc1": "MIDDLE JURASSIC",
  "wlbFormationWithHc2": "",
  "wlbAgeWithHc2": "",
  "wlbFormationWithHc3": "                    ",
  "wlbAgeWithHc3": "                    ",
  "wlbDrillingDays": "112",
  "wlbReentry": "NO",
  "wlbGeodeticDatum": "ED50  ",
  "wlbNsDeg": "57",
  "wlbNsMin": "45",
  "wlbNsSec": "15.19",
  "wlbNsCode": "N",
  "wlbEwDeg": "4",
  "wlbEwMin": "21",
  "wlbEwSec": "20.58",
  "wlbEwCode": "E",
  "wlbNsDecDeg": "57.754219",
  "wlbEwDesDeg": "4.355717",
  "wlbNsUtm": "6402299.56",
  "wlbEwUtm": "580684.43",
  "wlbUtmZone": "31",
  "wlbNamePart1": "9",
  "wlbNamePart2": "2",
  "wlbNamePart3": " ",
  "wlbNamePart4": "9",
  "wlbNamePart5": "S",
  "wlbNamePart6": "",
  "wlbPressReleaseUrl": " ",
  "wlbFactPageUrl": "http://factpages.npd.no/FactPages/Default.aspx?nav1=wellbore&nav2=PageView|Exploration|All&nav3=3703",
  "wlbFactMapUrl": "http://gis.npd.no/factmaps/html_21/?run=WellboreExpByNPDID&scale=100000&NPDID=3703",
  "wlbDiskosWellboreType": "initial             ",
  "wlbDiskosWellboreParent": "                                        ",
  "wlbWdssQcDate": "24.09.2002",
  "wlbReleasedDate": "18.10.2001",
  "wlbNpdidWellbore": "3703",
  "dscNpdidDiscovery": "112160",
  "fldNpdidField": "43807",
  "fclNpdidFacilityDrilling": "341331",
  "wlbNpdidWellboreReclass": "3911",
  "prlNpdidProductionLicence": "21716"
}