{
  "wlbWellboreName": "15/12-17 S",
  "wlbWell": "15/12-17",
  "wlbDrillingOperator": "Talisman Energy Norge AS",
  "wlbProductionLicence": "038 ",
  "wlbPurpose": "APPRAISAL",
  "wlbStatus": "P&A",
  "wlbContent": "GAS/CONDENSATE",
  "wlbWellType": "EXPLORATION",
  "wlbSubSea": " NO",
  "wlbEntryDate": "23.12.2006",
  "wlbCompletionDate": "04.02.2007",
  "wlbField": "REV",
  "wlbDrillPermit": "1127-L",
  "wlbDiscovery": "15/12-12 REV",
  "wlbDiscoveryWellbore": "NO",
  "wlbBottomHoleTemperature": "125",
  "wlbSeismicLocation": " ",
  "wlbMaxInclation": "45.74",
  "wlbKellyBushElevation": "43.0",
  "wlbFinalVerticalDepth": "2860.0",
  "wlbTotalDepth": "3371.0",
  "wlbWaterDepth": "87.0",
  "wlbKickOffPoint": "",
  "wlbAgeAtTd": "LATE PERMIAN        ",
  "wlbFormationAtTd": "ZECHSTEIN GP        ",
  "wlbMainArea": "North sea",
  "wlbDrillingFacility": "M\u00c6RSK GIANT",
  "wlbFacilityTypeDrilling": "JACK-UP 3 LEGS",
  "wlbDrillingFacilityFixedOrMoveable": "MOVEABLE",
  "wlbLicensingActivity": "3",
  "wlbMultilateral": "NO",
  "wlbPurposePlanned": "APPRAISAL",
  "wlbEntryYear": "2006",
  "wlbCompletionYear": "2007",
  "wlbReclassFromWellbore": "",
  "wlbReentryExplorationActivity": "",
  "wlbPlotSymbol": "17",
  "wlbFormationWithHc1": "INTRA HEATHER FM SS",
  "wlbAgeWithHc1": "LATE JURASSIC",
  "wlbFormationWithHc2": "",
  "wlbAgeWithHc2": "",
  "wlbFormationWithHc3": "                    ",
  "wlbAgeWithHc3": "                    ",
  "wlbDrillingDays": "44",
  "wlbReentry": "NO",
  "wlbGeodeticDatum": "ED50  ",
  "wlbNsDeg": "58",
  "wlbNsMin": "1",
  "wlbNsSec": "42.68",
  "wlbNsCode": "N",
  "wlbEwDeg": "1",
  "wlbEwMin": "55",
  "wlbEwSec": "23.46",
  "wlbEwCode": "E",
  "wlbNsDecDeg": "58.028522",
  "wlbEwDesDeg": "1.923183",
  "wlbNsUtm": "6432538.90",
  "wlbEwUtm": "436399.33",
  "wlbUtmZone": "31",
  "wlbNamePart1": "15",
  "wlbNamePart2": "12",
  "wlbNamePart3": " ",
  "wlbNamePart4": "17",
  "wlbNamePart5": "S",
  "wlbNamePart6": "",
  "wlbPressReleaseUrl": "http://www.npd.no/Norsk/Aktuelt/Pressemeldinger/2007/Pressemelding+7-2007+REV.htm",
  "wlbFactPageUrl": "http://factpages.npd.no/FactPages/Default.aspx?nav1=wellbore&nav2=PageView|Exploration|All&nav3=5442",
  "wlbFactMapUrl": "http://gis.npd.no/factmaps/html_21/?run=WellboreExpByNPDID&scale=100000&NPDID=5442",
  "wlbDiskosWellboreType": "initial             ",
  "wlbDiskosWellboreParent": "                                        ",
  "wlbWdssQcDate": "09.03.2009",
  "wlbReleasedDate": "04.02.2009",
  "wlbNpdidWellbore": "5442",
  "dscNpdidDiscovery": "1626017",
  "fldNpdidField": "4467554",
  "fclNpdidFacilityDrilling": "278245",
  "wlbNpdidWellboreReclass": "0",
  "prlNpdidProductionLicence": "21092"
}