{
  "wlbWellboreName": "34/10-49 S",
  "wlbWell": "34/10-49",
  "wlbDrillingOperator": "Statoil ASA (old)",
  "wlbProductionLicence": "050 ",
  "wlbPurpose": "WILDCAT",
  "wlbStatus": "P&A",
  "wlbContent": "OIL",
  "wlbWellType": "EXPLORATION",
  "wlbSubSea": " NO",
  "wlbEntryDate": "20.03.2006",
  "wlbCompletionDate": "01.05.2006",
  "wlbField": "GULLFAKS S\u00d8R",
  "wlbDrillPermit": "1099-L",
  "wlbDiscovery": "34/10-49 S ALUN",
  "wlbDiscoveryWellbore": "YES",
  "wlbBottomHoleTemperature": "105",
  "wlbSeismicLocation": "ST9607",
  "wlbMaxInclation": "72.00",
  "wlbKellyBushElevation": "21.5",
  "wlbFinalVerticalDepth": "3079.0",
  "wlbTotalDepth": "4126.0",
  "wlbWaterDepth": "138.0",
  "wlbKickOffPoint": "",
  "wlbAgeAtTd": "EARLY JURASSIC      ",
  "wlbFormationAtTd": "AMUNDSEN FM         ",
  "wlbMainArea": "North sea",
  "wlbDrillingFacility": "OCEAN VANGUARD",
  "wlbFacilityTypeDrilling": "SEMISUB STEEL",
  "wlbDrillingFacilityFixedOrMoveable": "MOVEABLE",
  "wlbLicensingActivity": "Awarded additionally to round 3",
  "wlbMultilateral": "NO",
  "wlbPurposePlanned": "WILDCAT",
  "wlbEntryYear": "2006",
  "wlbCompletionYear": "2006",
  "wlbReclassFromWellbore": "",
  "wlbReentryExplorationActivity": "",
  "wlbPlotSymbol": "5",
  "wlbFormationWithHc1": "BRENT GP",
  "wlbAgeWithHc1": "MIDDLE JURASSIC",
  "wlbFormationWithHc2": "STATFJORD GP",
  "wlbAgeWithHc2": "EARLY JURASSIC",
  "wlbFormationWithHc3": "                    ",
  "wlbAgeWithHc3": "                    ",
  "wlbDrillingDays": "43",
  "wlbReentry": "NO",
  "wlbGeodeticDatum": "ED50  ",
  "wlbNsDeg": "61",
  "wlbNsMin": "7",
  "wlbNsSec": "45.1",
  "wlbNsCode": "N",
  "wlbEwDeg": "2",
  "wlbEwMin": "5",
  "wlbEwSec": "26.2",
  "wlbEwCode": "E",
  "wlbNsDecDeg": "61.129194",
  "wlbEwDesDeg": "2.090611",
  "wlbNsUtm": "6777679.15",
  "wlbEwUtm": "451013.47",
  "wlbUtmZone": "31",
  "wlbNamePart1": "34",
  "wlbNamePart2": "10",
  "wlbNamePart3": " ",
  "wlbNamePart4": "49",
  "wlbNamePart5": "S",
  "wlbNamePart6": "",
  "wlbPressReleaseUrl": "http://www.npd.no/no/Nyheter/Resultat-av-leteboring/2006/3410-49-S-B-og-A/",
  "wlbFactPageUrl": "http://factpages.npd.no/FactPages/Default.aspx?nav1=wellbore&nav2=PageView|Exploration|All&nav3=5140",
  "wlbFactMapUrl": "http://gis.npd.no/factmaps/html_21/?run=WellboreExpByNPDID&scale=100000&NPDID=5140",
  "wlbDiskosWellboreType": "initial             ",
  "wlbDiskosWellboreParent": "                                        ",
  "wlbWdssQcDate": "18.12.2008",
  "wlbReleasedDate": "01.05.2008",
  "wlbNpdidWellbore": "5140",
  "dscNpdidDiscovery": "4038603",
  "fldNpdidField": "43699",
  "fclNpdidFacilityDrilling": "287902",
  "wlbNpdidWellboreReclass": "0",
  "prlNpdidProductionLicence": "21188"
}