{
  "wlbWellboreName": "30/10-2",
  "wlbWell": "30/10-2",
  "wlbDrillingOperator": "Esso Exploration and Production Norway A/S",
  "wlbProductionLicence": "030 ",
  "wlbPurpose": "WILDCAT",
  "wlbStatus": "P&A",
  "wlbContent": "GAS",
  "wlbWellType": "EXPLORATION",
  "wlbSubSea": " NO",
  "wlbEntryDate": "24.12.1973",
  "wlbCompletionDate": "28.03.1974",
  "wlbField": "ODIN",
  "wlbDrillPermit": "102-L",
  "wlbDiscovery": "30/10-2 ODIN",
  "wlbDiscoveryWellbore": "YES",
  "wlbBottomHoleTemperature": "77",
  "wlbSeismicLocation": "LINE CS 131  SP.26575",
  "wlbMaxInclation": "0.00",
  "wlbKellyBushElevation": "24.0",
  "wlbFinalVerticalDepth": "0.0",
  "wlbTotalDepth": "2755.0",
  "wlbWaterDepth": "104.0",
  "wlbKickOffPoint": "",
  "wlbAgeAtTd": "LATE CRETACEOUS     ",
  "wlbFormationAtTd": "HARDR\u00c5DE FM         ",
  "wlbMainArea": "North sea",
  "wlbDrillingFacility": "DRILLMASTER",
  "wlbFacilityTypeDrilling": "SEMISUB STEEL",
  "wlbDrillingFacilityFixedOrMoveable": "MOVEABLE",
  "wlbLicensingActivity": "2-A",
  "wlbMultilateral": "NO",
  "wlbPurposePlanned": "WILDCAT",
  "wlbEntryYear": "1973",
  "wlbCompletionYear": "1974",
  "wlbReclassFromWellbore": "",
  "wlbReentryExplorationActivity": "",
  "wlbPlotSymbol": "9",
  "wlbFormationWithHc1": "FRIGG FM",
  "wlbAgeWithHc1": "EOCENE",
  "wlbFormationWithHc2": "",
  "wlbAgeWithHc2": "",
  "wlbFormationWithHc3": "                    ",
  "wlbAgeWithHc3": "                    ",
  "wlbDrillingDays": "95",
  "wlbReentry": "NO",
  "wlbGeodeticDatum": "ED50  ",
  "wlbNsDeg": "60",
  "wlbNsMin": "4",
  "wlbNsSec": "58.87",
  "wlbNsCode": "N",
  "wlbEwDeg": "2",
  "wlbEwMin": "9",
  "wlbEwSec": "42.76",
  "wlbEwCode": "E",
  "wlbNsDecDeg": "60.083019",
  "wlbEwDesDeg": "2.161878",
  "wlbNsUtm": "6661108.48",
  "wlbEwUtm": "453367.16",
  "wlbUtmZone": "31",
  "wlbNamePart1": "30",
  "wlbNamePart2": "10",
  "wlbNamePart3": " ",
  "wlbNamePart4": "2",
  "wlbNamePart5": "",
  "wlbNamePart6": "",
  "wlbPressReleaseUrl": " ",
  "wlbFactPageUrl": "http://factpages.npd.no/FactPages/Default.aspx?nav1=wellbore&nav2=PageView|Exploration|All&nav3=392",
  "wlbFactMapUrl": "http://gis.npd.no/factmaps/html_21/?run=WellboreExpByNPDID&scale=100000&NPDID=392",
  "wlbDiskosWellboreType": "initial             ",
  "wlbDiskosWellboreParent": "                                        ",
  "wlbWdssQcDate": "29.06.2004",
  "wlbReleasedDate": "28.03.1976",
  "wlbNpdidWellbore": "392",
  "dscNpdidDiscovery": "44360",
  "fldNpdidField": "43610",
  "fclNpdidFacilityDrilling": "288172",
  "wlbNpdidWellboreReclass": "0",
  "prlNpdidProductionLicence": "21028"
}