{
  "wlbWellboreName": "2/1-10",
  "wlbWell": "2/1-10",
  "wlbDrillingOperator": "BP Norway Limited  U.A.",
  "wlbProductionLicence": "164 ",
  "wlbPurpose": "WILDCAT",
  "wlbStatus": "P&A",
  "wlbContent": "OIL SHOWS",
  "wlbWellType": "EXPLORATION",
  "wlbSubSea": " NO",
  "wlbEntryDate": "09.11.1991",
  "wlbCompletionDate": "14.01.1992",
  "wlbField": "",
  "wlbDrillPermit": "703-L",
  "wlbDiscovery": "",
  "wlbDiscoveryWellbore": "NO",
  "wlbBottomHoleTemperature": "163",
  "wlbSeismicLocation": "GYDA 3D  IN LINE  122   X- LINE  1006",
  "wlbMaxInclation": "6.65",
  "wlbKellyBushElevation": "23.0",
  "wlbFinalVerticalDepth": "4523.1",
  "wlbTotalDepth": "4525.0",
  "wlbWaterDepth": "66.0",
  "wlbKickOffPoint": "",
  "wlbAgeAtTd": "TRIASSIC            ",
  "wlbFormationAtTd": "SKAGERRAK FM        ",
  "wlbMainArea": "North sea",
  "wlbDrillingFacility": "ROSS ISLE",
  "wlbFacilityTypeDrilling": "SEMISUB STEEL",
  "wlbDrillingFacilityFixedOrMoveable": "MOVEABLE",
  "wlbLicensingActivity": "13",
  "wlbMultilateral": "NO",
  "wlbPurposePlanned": "WILDCAT",
  "wlbEntryYear": "1991",
  "wlbCompletionYear": "1992",
  "wlbReclassFromWellbore": "",
  "wlbReentryExplorationActivity": "",
  "wlbPlotSymbol": "12",
  "wlbFormationWithHc1": "",
  "wlbAgeWithHc1": "",
  "wlbFormationWithHc2": "",
  "wlbAgeWithHc2": "",
  "wlbFormationWithHc3": "                    ",
  "wlbAgeWithHc3": "                    ",
  "wlbDrillingDays": "67",
  "wlbReentry": "NO",
  "wlbGeodeticDatum": "ED50  ",
  "wlbNsDeg": "56",
  "wlbNsMin": "57",
  "wlbNsSec": "53.61",
  "wlbNsCode": "N",
  "wlbEwDeg": "3",
  "wlbEwMin": "1",
  "wlbEwSec": "19.7",
  "wlbEwCode": "E",
  "wlbNsDecDeg": "56.964892",
  "wlbEwDesDeg": "3.022139",
  "wlbNsUtm": "6313619.42",
  "wlbEwUtm": "501346.22",
  "wlbUtmZone": "31",
  "wlbNamePart1": "2",
  "wlbNamePart2": "1",
  "wlbNamePart3": " ",
  "wlbNamePart4": "10",
  "wlbNamePart5": "",
  "wlbNamePart6": "",
  "wlbPressReleaseUrl": " ",
  "wlbFactPageUrl": "http://factpages.npd.no/FactPages/Default.aspx?nav1=wellbore&nav2=PageView|Exploration|All&nav3=1865",
  "wlbFactMapUrl": "http://gis.npd.no/factmaps/html_21/?run=WellboreExpByNPDID&scale=100000&NPDID=1865",
  "wlbDiskosWellboreType": "initial             ",
  "wlbDiskosWellboreParent": "                                        ",
  "wlbWdssQcDate": "24.09.2002",
  "wlbReleasedDate": "14.01.1994",
  "wlbNpdidWellbore": "1865",
  "dscNpdidDiscovery": "",
  "fldNpdidField": "",
  "fclNpdidFacilityDrilling": "296245",
  "wlbNpdidWellboreReclass": "0",
  "prlNpdidProductionLicence": "22124"
}