{
  "wlbWellboreName": "7321/7-1",
  "wlbWell": "7321/7-1",
  "wlbDrillingOperator": "Mobil Exploration Norway INC",
  "wlbProductionLicence": "140 ",
  "wlbPurpose": "WILDCAT",
  "wlbStatus": "P&A",
  "wlbContent": "GAS SHOWS",
  "wlbWellType": "EXPLORATION",
  "wlbSubSea": " NO",
  "wlbEntryDate": "26.06.1988",
  "wlbCompletionDate": "22.10.1988",
  "wlbField": "",
  "wlbDrillPermit": "582-L",
  "wlbDiscovery": "",
  "wlbDiscoveryWellbore": "NO",
  "wlbBottomHoleTemperature": "121",
  "wlbSeismicLocation": "D-16-84   SP 3410",
  "wlbMaxInclation": "7.50",
  "wlbKellyBushElevation": "23.5",
  "wlbFinalVerticalDepth": "3545.0",
  "wlbTotalDepth": "3550.0",
  "wlbWaterDepth": "475.0",
  "wlbKickOffPoint": "",
  "wlbAgeAtTd": "MIDDLE TRIASSIC     ",
  "wlbFormationAtTd": "SNADD FM            ",
  "wlbMainArea": "Barents sea",
  "wlbDrillingFacility": "ROSS RIG (2)",
  "wlbFacilityTypeDrilling": "SEMISUB STEEL",
  "wlbDrillingFacilityFixedOrMoveable": "MOVEABLE",
  "wlbLicensingActivity": "11-B",
  "wlbMultilateral": "NO",
  "wlbPurposePlanned": "WILDCAT",
  "wlbEntryYear": "1988",
  "wlbCompletionYear": "1988",
  "wlbReclassFromWellbore": "",
  "wlbReentryExplorationActivity": "",
  "wlbPlotSymbol": "12",
  "wlbFormationWithHc1": "",
  "wlbAgeWithHc1": "",
  "wlbFormationWithHc2": "",
  "wlbAgeWithHc2": "",
  "wlbFormationWithHc3": "                    ",
  "wlbAgeWithHc3": "                    ",
  "wlbDrillingDays": "119",
  "wlbReentry": "NO",
  "wlbGeodeticDatum": "ED50  ",
  "wlbNsDeg": "73",
  "wlbNsMin": "25",
  "wlbNsSec": "55.57",
  "wlbNsCode": "N",
  "wlbEwDeg": "21",
  "wlbEwMin": "4",
  "wlbEwSec": "31.75",
  "wlbEwCode": "E",
  "wlbNsDecDeg": "73.432103",
  "wlbEwDesDeg": "21.075486",
  "wlbNsUtm": "8158249.22",
  "wlbEwUtm": "311704.77",
  "wlbUtmZone": "35",
  "wlbNamePart1": "7321",
  "wlbNamePart2": "7",
  "wlbNamePart3": " ",
  "wlbNamePart4": "1",
  "wlbNamePart5": "",
  "wlbNamePart6": "",
  "wlbPressReleaseUrl": " ",
  "wlbFactPageUrl": "http://factpages.npd.no/FactPages/Default.aspx?nav1=wellbore&nav2=PageView|Exploration|All&nav3=1284",
  "wlbFactMapUrl": "http://gis.npd.no/factmaps/html_21/?run=WellboreExpByNPDID&scale=100000&NPDID=1284",
  "wlbDiskosWellboreType": "initial             ",
  "wlbDiskosWellboreParent": "                                        ",
  "wlbWdssQcDate": "05.01.2005",
  "wlbReleasedDate": "22.10.1990",
  "wlbNpdidWellbore": "1284",
  "dscNpdidDiscovery": "",
  "fldNpdidField": "",
  "fclNpdidFacilityDrilling": "294382",
  "wlbNpdidWellboreReclass": "0",
  "prlNpdidProductionLicence": "21932"
}