{
  "wlbWellboreName": "6407/10-3",
  "wlbWell": "6407/10-3",
  "wlbDrillingOperator": "Norsk Hydro Produksjon AS",
  "wlbProductionLicence": "132 ",
  "wlbPurpose": "WILDCAT",
  "wlbStatus": "P&A",
  "wlbContent": "SHOWS",
  "wlbWellType": "EXPLORATION",
  "wlbSubSea": " NO",
  "wlbEntryDate": "29.05.1992",
  "wlbCompletionDate": "27.06.1992",
  "wlbField": "",
  "wlbDrillPermit": "721-L",
  "wlbDiscovery": "",
  "wlbDiscoveryWellbore": "NO",
  "wlbBottomHoleTemperature": "94",
  "wlbSeismicLocation": "NH 8411-404 & SP. 460",
  "wlbMaxInclation": "2.50",
  "wlbKellyBushElevation": "23.5",
  "wlbFinalVerticalDepth": "2972.0",
  "wlbTotalDepth": "2973.0",
  "wlbWaterDepth": "323.5",
  "wlbKickOffPoint": "",
  "wlbAgeAtTd": "PRE-DEVONIAN        ",
  "wlbFormationAtTd": "BASEMENT            ",
  "wlbMainArea": "Norwegian sea",
  "wlbDrillingFacility": "TRANSOCEAN 8",
  "wlbFacilityTypeDrilling": "SEMISUB STEEL",
  "wlbDrillingFacilityFixedOrMoveable": "MOVEABLE",
  "wlbLicensingActivity": "11-A",
  "wlbMultilateral": "NO",
  "wlbPurposePlanned": "WILDCAT",
  "wlbEntryYear": "1992",
  "wlbCompletionYear": "1992",
  "wlbReclassFromWellbore": "",
  "wlbReentryExplorationActivity": "",
  "wlbPlotSymbol": "12",
  "wlbFormationWithHc1": "",
  "wlbAgeWithHc1": "",
  "wlbFormationWithHc2": "",
  "wlbAgeWithHc2": "",
  "wlbFormationWithHc3": "                    ",
  "wlbAgeWithHc3": "                    ",
  "wlbDrillingDays": "30",
  "wlbReentry": "NO",
  "wlbGeodeticDatum": "ED50  ",
  "wlbNsDeg": "64",
  "wlbNsMin": "6",
  "wlbNsSec": "11.66",
  "wlbNsCode": "N",
  "wlbEwDeg": "7",
  "wlbEwMin": "18",
  "wlbEwSec": "11.43",
  "wlbEwCode": "E",
  "wlbNsDecDeg": "64.103239",
  "wlbEwDesDeg": "7.303175",
  "wlbNsUtm": "7109795.67",
  "wlbEwUtm": "417314.23",
  "wlbUtmZone": "32",
  "wlbNamePart1": "6407",
  "wlbNamePart2": "10",
  "wlbNamePart3": " ",
  "wlbNamePart4": "3",
  "wlbNamePart5": "",
  "wlbNamePart6": "",
  "wlbPressReleaseUrl": " ",
  "wlbFactPageUrl": "http://factpages.npd.no/FactPages/Default.aspx?nav1=wellbore&nav2=PageView|Exploration|All&nav3=1927",
  "wlbFactMapUrl": "http://gis.npd.no/factmaps/html_21/?run=WellboreExpByNPDID&scale=100000&NPDID=1927",
  "wlbDiskosWellboreType": "initial             ",
  "wlbDiskosWellboreParent": "                                        ",
  "wlbWdssQcDate": "02.03.2004",
  "wlbReleasedDate": "27.06.1994",
  "wlbNpdidWellbore": "1927",
  "dscNpdidDiscovery": "",
  "fldNpdidField": "",
  "fclNpdidFacilityDrilling": "296677",
  "wlbNpdidWellboreReclass": "0",
  "prlNpdidProductionLicence": "21868"
}