{
  "wlbWellboreName": "6305/4-1",
  "wlbWell": "6305/4-1",
  "wlbDrillingOperator": "Norsk Hydro Produksjon AS",
  "wlbProductionLicence": "209 ",
  "wlbPurpose": "APPRAISAL",
  "wlbStatus": "P&A",
  "wlbContent": "GAS",
  "wlbWellType": "EXPLORATION",
  "wlbSubSea": " NO",
  "wlbEntryDate": "14.03.2002",
  "wlbCompletionDate": "03.06.2002",
  "wlbField": "ORMEN LANGE",
  "wlbDrillPermit": "1025-L",
  "wlbDiscovery": "6305/5-1 ORMEN LANGE",
  "wlbDiscoveryWellbore": "NO",
  "wlbBottomHoleTemperature": "84",
  "wlbSeismicLocation": "inline 4152 & x-line 5028",
  "wlbMaxInclation": "5.70",
  "wlbKellyBushElevation": "25.0",
  "wlbFinalVerticalDepth": "2974.0",
  "wlbTotalDepth": "2975.0",
  "wlbWaterDepth": "1002.0",
  "wlbKickOffPoint": "",
  "wlbAgeAtTd": "LATE CRETACEOUS     ",
  "wlbFormationAtTd": "SPRINGAR FM         ",
  "wlbMainArea": "Norwegian sea",
  "wlbDrillingFacility": "SCARABEO 5",
  "wlbFacilityTypeDrilling": "SEMISUB STEEL",
  "wlbDrillingFacilityFixedOrMoveable": "MOVEABLE",
  "wlbLicensingActivity": "15",
  "wlbMultilateral": "NO",
  "wlbPurposePlanned": "APPRAISAL",
  "wlbEntryYear": "2002",
  "wlbCompletionYear": "2002",
  "wlbReclassFromWellbore": "",
  "wlbReentryExplorationActivity": "",
  "wlbPlotSymbol": "9",
  "wlbFormationWithHc1": "EGGA FM (INFORMAL)",
  "wlbAgeWithHc1": "PALEOCENE",
  "wlbFormationWithHc2": "",
  "wlbAgeWithHc2": "",
  "wlbFormationWithHc3": "                    ",
  "wlbAgeWithHc3": "                    ",
  "wlbDrillingDays": "82",
  "wlbReentry": "NO",
  "wlbGeodeticDatum": "ED50  ",
  "wlbNsDeg": "63",
  "wlbNsMin": "34",
  "wlbNsSec": "17.76",
  "wlbNsCode": "N",
  "wlbEwDeg": "5",
  "wlbEwMin": "17",
  "wlbEwSec": "55.93",
  "wlbEwCode": "E",
  "wlbNsDecDeg": "63.571600",
  "wlbEwDesDeg": "5.298869",
  "wlbNsUtm": "7051501.85",
  "wlbEwUtm": "614148.32",
  "wlbUtmZone": "31",
  "wlbNamePart1": "6305",
  "wlbNamePart2": "4",
  "wlbNamePart3": " ",
  "wlbNamePart4": "1",
  "wlbNamePart5": "",
  "wlbNamePart6": "",
  "wlbPressReleaseUrl": "http://www.npd.no/no/Nyheter/Resultat-av-leteboring/2002/63054-1",
  "wlbFactPageUrl": "http://factpages.npd.no/FactPages/Default.aspx?nav1=wellbore&nav2=PageView|Exploration|All&nav3=4441",
  "wlbFactMapUrl": "http://gis.npd.no/factmaps/html_21/?run=WellboreExpByNPDID&scale=100000&NPDID=4441",
  "wlbDiskosWellboreType": "initial             ",
  "wlbDiskosWellboreParent": "                                        ",
  "wlbWdssQcDate": "29.06.2004",
  "wlbReleasedDate": "03.06.2004",
  "wlbNpdidWellbore": "4441",
  "dscNpdidDiscovery": "44822",
  "fldNpdidField": "2762452",
  "fclNpdidFacilityDrilling": "294058",
  "wlbNpdidWellboreReclass": "0",
  "prlNpdidProductionLicence": "22484"
}