{
  "wlbWellboreName": "6406/3-6",
  "wlbWell": "6406/3-6",
  "wlbDrillingOperator": "Statoil ASA (old)",
  "wlbProductionLicence": "091 ",
  "wlbPurpose": "APPRAISAL",
  "wlbStatus": "P&A",
  "wlbContent": "OIL/GAS",
  "wlbWellType": "EXPLORATION",
  "wlbSubSea": " NO",
  "wlbEntryDate": "21.09.2002",
  "wlbCompletionDate": "15.11.2002",
  "wlbField": "TYRIHANS",
  "wlbDrillPermit": "1040-L",
  "wlbDiscovery": "6407/1-2 TYRIHANS S\u00d8R",
  "wlbDiscoveryWellbore": "NO",
  "wlbBottomHoleTemperature": "151",
  "wlbSeismicLocation": "inline 484 & x-line 927: ST9503R99",
  "wlbMaxInclation": "3.70",
  "wlbKellyBushElevation": "24.0",
  "wlbFinalVerticalDepth": "4174.0",
  "wlbTotalDepth": "4175.0",
  "wlbWaterDepth": "273.0",
  "wlbKickOffPoint": "",
  "wlbAgeAtTd": "EARLY JURASSIC      ",
  "wlbFormationAtTd": "TILJE FM            ",
  "wlbMainArea": "Norwegian sea",
  "wlbDrillingFacility": "STENA DON",
  "wlbFacilityTypeDrilling": "SEMISUB STEEL",
  "wlbDrillingFacilityFixedOrMoveable": "MOVEABLE",
  "wlbLicensingActivity": "8",
  "wlbMultilateral": "NO",
  "wlbPurposePlanned": "APPRAISAL",
  "wlbEntryYear": "2002",
  "wlbCompletionYear": "2002",
  "wlbReclassFromWellbore": "",
  "wlbReentryExplorationActivity": "",
  "wlbPlotSymbol": "13",
  "wlbFormationWithHc1": "GARN FM",
  "wlbAgeWithHc1": "MIDDLE JURASSIC",
  "wlbFormationWithHc2": "ILE FM",
  "wlbAgeWithHc2": "MIDDLE JURASSIC",
  "wlbFormationWithHc3": "                    ",
  "wlbAgeWithHc3": "                    ",
  "wlbDrillingDays": "56",
  "wlbReentry": "NO",
  "wlbGeodeticDatum": "ED50  ",
  "wlbNsDeg": "64",
  "wlbNsMin": "47",
  "wlbNsSec": "43.56",
  "wlbNsCode": "N",
  "wlbEwDeg": "6",
  "wlbEwMin": "57",
  "wlbEwSec": "55.17",
  "wlbEwCode": "E",
  "wlbNsDecDeg": "64.795433",
  "wlbEwDesDeg": "6.965325",
  "wlbNsUtm": "7187388.89",
  "wlbEwUtm": "403326.40",
  "wlbUtmZone": "32",
  "wlbNamePart1": "6406",
  "wlbNamePart2": "3",
  "wlbNamePart3": " ",
  "wlbNamePart4": "6",
  "wlbNamePart5": "",
  "wlbNamePart6": "",
  "wlbPressReleaseUrl": "http://www.npd.no/no/Nyheter/Resultat-av-leteboring/2002/64063-6/",
  "wlbFactPageUrl": "http://factpages.npd.no/FactPages/Default.aspx?nav1=wellbore&nav2=PageView|Exploration|All&nav3=4589",
  "wlbFactMapUrl": "http://gis.npd.no/factmaps/html_21/?run=WellboreExpByNPDID&scale=100000&NPDID=4589",
  "wlbDiskosWellboreType": "initial             ",
  "wlbDiskosWellboreParent": "                                        ",
  "wlbWdssQcDate": "01.12.2004",
  "wlbReleasedDate": "15.11.2004",
  "wlbNpdidWellbore": "4589",
  "dscNpdidDiscovery": "44852",
  "fldNpdidField": "3960848",
  "fclNpdidFacilityDrilling": "297649",
  "wlbNpdidWellboreReclass": "0",
  "prlNpdidProductionLicence": "21532"
}