{
  "wlbWellboreName": "6506/11-1",
  "wlbWell": "6506/11-1",
  "wlbDrillingOperator": "Den norske stats oljeselskap a.s",
  "wlbProductionLicence": "134 ",
  "wlbPurpose": "WILDCAT",
  "wlbStatus": "P&A",
  "wlbContent": "GAS SHOWS",
  "wlbWellType": "EXPLORATION",
  "wlbSubSea": " NO",
  "wlbEntryDate": "30.12.1987",
  "wlbCompletionDate": "31.03.1988",
  "wlbField": "",
  "wlbDrillPermit": "569-L",
  "wlbDiscovery": "",
  "wlbDiscoveryWellbore": "NO",
  "wlbBottomHoleTemperature": "143",
  "wlbSeismicLocation": "ST 8403 - 860 SP. 622",
  "wlbMaxInclation": "10.00",
  "wlbKellyBushElevation": "29.0",
  "wlbFinalVerticalDepth": "4672.0",
  "wlbTotalDepth": "4679.0",
  "wlbWaterDepth": "246.0",
  "wlbKickOffPoint": "",
  "wlbAgeAtTd": "EARLY JURASSIC      ",
  "wlbFormationAtTd": "ÅRE FM              ",
  "wlbMainArea": "Norwegian sea",
  "wlbDrillingFacility": "DYVI DELTA",
  "wlbFacilityTypeDrilling": "SEMISUB STEEL",
  "wlbDrillingFacilityFixedOrMoveable": "MOVEABLE",
  "wlbLicensingActivity": "11-A",
  "wlbMultilateral": "NO",
  "wlbPurposePlanned": "WILDCAT",
  "wlbEntryYear": "1987",
  "wlbCompletionYear": "1988",
  "wlbReclassFromWellbore": "",
  "wlbReentryExplorationActivity": "",
  "wlbPlotSymbol": "12",
  "wlbFormationWithHc1": "",
  "wlbAgeWithHc1": "",
  "wlbFormationWithHc2": "",
  "wlbAgeWithHc2": "",
  "wlbFormationWithHc3": "                    ",
  "wlbAgeWithHc3": "                    ",
  "wlbDrillingDays": "93",
  "wlbReentry": "NO",
  "wlbGeodeticDatum": "ED50  ",
  "wlbNsDeg": "65",
  "wlbNsMin": "11",
  "wlbNsSec": "4.49",
  "wlbNsCode": "N",
  "wlbEwDeg": "6",
  "wlbEwMin": "39",
  "wlbEwSec": "53.88",
  "wlbEwCode": "E",
  "wlbNsDecDeg": "65.184581",
  "wlbEwDesDeg": "6.664967",
  "wlbNsUtm": "7231229.82",
  "wlbEwUtm": "390662.03",
  "wlbUtmZone": "32",
  "wlbNamePart1": "6506",
  "wlbNamePart2": "11",
  "wlbNamePart3": " ",
  "wlbNamePart4": "1",
  "wlbNamePart5": "",
  "wlbNamePart6": "",
  "wlbPressReleaseUrl": " ",
  "wlbFactPageUrl": "http://factpages.npd.no/FactPages/Default.aspx?nav1=wellbore&nav2=PageView|Exploration|All&nav3=1216",
  "wlbFactMapUrl": "http://gis.npd.no/factmaps/html_21/?run=WellboreExpByNPDID&scale=100000&NPDID=1216",
  "wlbDiskosWellboreType": "initial             ",
  "wlbDiskosWellboreParent": "                                        ",
  "wlbWdssQcDate": "02.03.2004",
  "wlbReleasedDate": "31.03.1990",
  "wlbNpdidWellbore": "1216",
  "dscNpdidDiscovery": "",
  "fldNpdidField": "",
  "fclNpdidFacilityDrilling": "287821",
  "wlbNpdidWellboreReclass": "0",
  "prlNpdidProductionLicence": "21884"
}