{
  "wlbWellboreName": "15/9-4",
  "wlbWell": "15/9-4",
  "wlbDrillingOperator": "Den norske stats oljeselskap a.s",
  "wlbProductionLicence": "046 ",
  "wlbPurpose": "APPRAISAL",
  "wlbStatus": "P&A",
  "wlbContent": "GAS/CONDENSATE",
  "wlbWellType": "EXPLORATION",
  "wlbSubSea": " NO",
  "wlbEntryDate": "04.04.1979",
  "wlbCompletionDate": "14.06.1979",
  "wlbField": "SLEIPNER VEST",
  "wlbDrillPermit": "213-L",
  "wlbDiscovery": "15/6-3 SLEIPNER VEST",
  "wlbDiscoveryWellbore": "NO",
  "wlbBottomHoleTemperature": "112",
  "wlbSeismicLocation": "Line 610-163 .SP 355",
  "wlbMaxInclation": "1.90",
  "wlbKellyBushElevation": "25.0",
  "wlbFinalVerticalDepth": "3716.0",
  "wlbTotalDepth": "3716.0",
  "wlbWaterDepth": "102.0",
  "wlbKickOffPoint": "",
  "wlbAgeAtTd": "TRIASSIC            ",
  "wlbFormationAtTd": "SKAGERRAK FM        ",
  "wlbMainArea": "North sea",
  "wlbDrillingFacility": "ROSS RIG (1)",
  "wlbFacilityTypeDrilling": "SEMISUB STEEL",
  "wlbDrillingFacilityFixedOrMoveable": "MOVEABLE",
  "wlbLicensingActivity": "3",
  "wlbMultilateral": "NO",
  "wlbPurposePlanned": "WILDCAT",
  "wlbEntryYear": "1979",
  "wlbCompletionYear": "1979",
  "wlbReclassFromWellbore": "",
  "wlbReentryExplorationActivity": "",
  "wlbPlotSymbol": "17",
  "wlbFormationWithHc1": "HUGIN FM",
  "wlbAgeWithHc1": "MIDDLE JURASSIC",
  "wlbFormationWithHc2": "",
  "wlbAgeWithHc2": "",
  "wlbFormationWithHc3": "                    ",
  "wlbAgeWithHc3": "                    ",
  "wlbDrillingDays": "72",
  "wlbReentry": "NO",
  "wlbGeodeticDatum": "ED50  ",
  "wlbNsDeg": "58",
  "wlbNsMin": "24",
  "wlbNsSec": "0.26",
  "wlbNsCode": "N",
  "wlbEwDeg": "1",
  "wlbEwMin": "47",
  "wlbEwSec": "6.93",
  "wlbEwCode": "E",
  "wlbNsDecDeg": "58.400072",
  "wlbEwDesDeg": "1.785258",
  "wlbNsUtm": "6474041.91",
  "wlbEwUtm": "428999.05",
  "wlbUtmZone": "31",
  "wlbNamePart1": "15",
  "wlbNamePart2": "9",
  "wlbNamePart3": " ",
  "wlbNamePart4": "4",
  "wlbNamePart5": "",
  "wlbNamePart6": "",
  "wlbPressReleaseUrl": " ",
  "wlbFactPageUrl": "http://factpages.npd.no/FactPages/Default.aspx?nav1=wellbore&nav2=PageView|Exploration|All&nav3=325",
  "wlbFactMapUrl": "http://gis.npd.no/factmaps/html_21/?run=WellboreExpByNPDID&scale=100000&NPDID=325",
  "wlbDiskosWellboreType": "initial             ",
  "wlbDiskosWellboreParent": "                                        ",
  "wlbWdssQcDate": "08.04.2015",
  "wlbReleasedDate": "14.06.1981",
  "wlbNpdidWellbore": "325",
  "dscNpdidDiscovery": "43910",
  "fldNpdidField": "43457",
  "fclNpdidFacilityDrilling": "446033",
  "wlbNpdidWellboreReclass": "0",
  "prlNpdidProductionLicence": "21156"
}