{
  "wlbWellboreName": "6406/2-5 A",
  "wlbWell": "6406/2-5",
  "wlbDrillingOperator": "Saga Petroleum ASA",
  "wlbProductionLicence": "199 ",
  "wlbPurpose": "APPRAISAL",
  "wlbStatus": "P&A",
  "wlbContent": "GAS/CONDENSATE",
  "wlbWellType": "EXPLORATION",
  "wlbSubSea": " NO",
  "wlbEntryDate": "02.10.1997",
  "wlbCompletionDate": "23.02.1998",
  "wlbField": "KRISTIN",
  "wlbDrillPermit": "908-L",
  "wlbDiscovery": "6406/2-3 KRISTIN",
  "wlbDiscoveryWellbore": "NO",
  "wlbBottomHoleTemperature": "175",
  "wlbSeismicLocation": "HWM 94- ROW 2500 & COLUMN 1152",
  "wlbMaxInclation": "37.50",
  "wlbKellyBushElevation": "23.0",
  "wlbFinalVerticalDepth": "4956.0",
  "wlbTotalDepth": "5600.0",
  "wlbWaterDepth": "341.0",
  "wlbKickOffPoint": "",
  "wlbAgeAtTd": "EARLY JURASSIC      ",
  "wlbFormationAtTd": "ROR FM              ",
  "wlbMainArea": "Norwegian sea",
  "wlbDrillingFacility": "DEEPSEA BERGEN",
  "wlbFacilityTypeDrilling": "SEMISUB STEEL",
  "wlbDrillingFacilityFixedOrMoveable": "MOVEABLE",
  "wlbLicensingActivity": "14",
  "wlbMultilateral": "NO",
  "wlbPurposePlanned": "APPRAISAL",
  "wlbEntryYear": "1997",
  "wlbCompletionYear": "1998",
  "wlbReclassFromWellbore": "",
  "wlbReentryExplorationActivity": "",
  "wlbPlotSymbol": "17",
  "wlbFormationWithHc1": "GARN FM",
  "wlbAgeWithHc1": "MIDDLE JURASSIC",
  "wlbFormationWithHc2": "ILE FM",
  "wlbAgeWithHc2": "MIDDLE JURASSIC",
  "wlbFormationWithHc3": "                    ",
  "wlbAgeWithHc3": "                    ",
  "wlbDrillingDays": "145",
  "wlbReentry": "NO",
  "wlbGeodeticDatum": "ED50  ",
  "wlbNsDeg": "64",
  "wlbNsMin": "55",
  "wlbNsSec": "53.83",
  "wlbNsCode": "N",
  "wlbEwDeg": "6",
  "wlbEwMin": "26",
  "wlbEwSec": "58.65",
  "wlbEwCode": "E",
  "wlbNsDecDeg": "64.931619",
  "wlbEwDesDeg": "6.449625",
  "wlbNsUtm": "7203444.56",
  "wlbEwUtm": "379444.85",
  "wlbUtmZone": "32",
  "wlbNamePart1": "6406",
  "wlbNamePart2": "2",
  "wlbNamePart3": " ",
  "wlbNamePart4": "5",
  "wlbNamePart5": "A",
  "wlbNamePart6": "",
  "wlbPressReleaseUrl": " ",
  "wlbFactPageUrl": "http://factpages.npd.no/FactPages/Default.aspx?nav1=wellbore&nav2=PageView|Exploration|All&nav3=3213",
  "wlbFactMapUrl": "http://gis.npd.no/factmaps/html_21/?run=WellboreExpByNPDID&scale=100000&NPDID=3213",
  "wlbDiskosWellboreType": "sidetrack           ",
  "wlbDiskosWellboreParent": "6406/2-5                                ",
  "wlbWdssQcDate": "24.09.2002",
  "wlbReleasedDate": "23.02.2000",
  "wlbNpdidWellbore": "3213",
  "dscNpdidDiscovery": "44840",
  "fldNpdidField": "1854729",
  "fclNpdidFacilityDrilling": "287983",
  "wlbNpdidWellboreReclass": "0",
  "prlNpdidProductionLicence": "22404"
}